django_skote_components-1.0.0.dist-info/licenses/LICENSE
skote_components/__init__.py
skote_components/apps.py
skote_components/static/skote/css/app.min.css
skote_components/static/skote/css/bootstrap.min.css
skote_components/static/skote/css/icons.min.css
skote_components/static/skote/fonts/boxicons.woff2
skote_components/static/skote/fonts/dripicons-v2.woff
skote_components/static/skote/fonts/fa-brands-400.woff2
skote_components/static/skote/fonts/fa-regular-400.woff2
skote_components/static/skote/fonts/fa-solid-900.woff2
skote_components/static/skote/fonts/materialdesignicons-webfont.woff2
skote_components/static/skote/images/bg-auth-overlay.png
skote_components/static/skote/images/coming-soon.svg
skote_components/static/skote/images/error-img.png
skote_components/static/skote/images/favicon.ico
skote_components/static/skote/images/jobs.png
skote_components/static/skote/images/logo-dark.png
skote_components/static/skote/images/logo-light.png
skote_components/static/skote/images/logo-light.svg
skote_components/static/skote/images/logo.svg
skote_components/static/skote/images/maintenance.svg
skote_components/static/skote/images/megamenu-img.png
skote_components/static/skote/images/profile-img.png
skote_components/static/skote/images/verification-img.png
skote_components/static/skote/images/brands/bitbucket.png
skote_components/static/skote/images/brands/dribbble.png
skote_components/static/skote/images/brands/dropbox.png
skote_components/static/skote/images/brands/github.png
skote_components/static/skote/images/brands/mail_chimp.png
skote_components/static/skote/images/brands/slack.png
skote_components/static/skote/images/clients/1.png
skote_components/static/skote/images/clients/2.png
skote_components/static/skote/images/clients/3.png
skote_components/static/skote/images/clients/4.png
skote_components/static/skote/images/clients/5.png
skote_components/static/skote/images/clients/6.png
skote_components/static/skote/images/companies/adobe-photoshop.svg
skote_components/static/skote/images/companies/adobe.svg
django_skote_components-1.0.0.dist-info/METADATA
django_skote_components-1.0.0.dist-info/WHEEL
django_skote_components-1.0.0.dist-info/top_level.txt
django_skote_components-1.0.0.dist-info/RECORD
