Metadata-Version: 2.4
Name: django-skote-components
Version: 1.0.0
Summary: A comprehensive Django component library based on the Skote Bootstrap 5 Admin Template
Author-email: Ralph Vincent <your.email@example.com>
Maintainer-email: Ralph Vincent <your.email@example.com>
License: MIT
Project-URL: Homepage, https://github.com/yourusername/django-skote-components
Project-URL: Documentation, https://github.com/yourusername/django-skote-components#readme
Project-URL: Repository, https://github.com/yourusername/django-skote-components
Project-URL: Issues, https://github.com/yourusername/django-skote-components/issues
Keywords: django,bootstrap,bootstrap5,admin,dashboard,template,components,ui,skote,theme
Classifier: Development Status :: 4 - Beta
Classifier: Environment :: Web Environment
Classifier: Framework :: Django
Classifier: Framework :: Django :: 3.2
Classifier: Framework :: Django :: 4.0
Classifier: Framework :: Django :: 4.1
Classifier: Framework :: Django :: 4.2
Classifier: Framework :: Django :: 5.0
Classifier: Intended Audience :: Developers
Classifier: License :: OSI Approved :: MIT License
Classifier: Operating System :: OS Independent
Classifier: Programming Language :: Python
Classifier: Programming Language :: Python :: 3
Classifier: Programming Language :: Python :: 3.8
Classifier: Programming Language :: Python :: 3.9
Classifier: Programming Language :: Python :: 3.10
Classifier: Programming Language :: Python :: 3.11
Classifier: Programming Language :: Python :: 3.12
Classifier: Topic :: Internet :: WWW/HTTP
Classifier: Topic :: Internet :: WWW/HTTP :: Dynamic Content
Classifier: Topic :: Software Development :: Libraries :: Python Modules
Requires-Python: >=3.8
License-File: LICENSE
Requires-Dist: Django>=3.2
Provides-Extra: dev
Requires-Dist: build>=0.10.0; extra == "dev"
Requires-Dist: twine>=4.0.0; extra == "dev"
Dynamic: license-file
